elsewhere_login-0.1.dist-info/METADATA
elsewhere_login-0.1.dist-info/RECORD
elsewhere_login-0.1.dist-info/WHEEL
elsewhere_login-0.1.dist-info/top_level.txt
ew_login/__init__.py
ew_login/login.py
