Metadata-Version: 2.1
Name: elsewhere-login
Version: 0.1
Summary: Authentication wrapper for Auth0
Home-page: https://gitlab.com/piar301/auth0-login
Author: Billy Lapatas
Author-email: piar301@gmail.com
License: MIT
Platform: UNKNOWN
Requires-Dist: Flask
Requires-Dist: flask-oidc
